{
    "leaderboard": [
        {
            "username": "osian​",
            "score": 300
        },
        {
            "username": "molly​",
            "score": 275
        },
        {
            "username": "rob​",
            "score": 200
        },
        {
            "username": "Drew",
            "score": 172
        },
        {
            "username": "OSIAN​",
            "score": 150
        },
        {
            "username": "Teddy​",
            "score": 150
        },
        {
            "username": "Jordan",
            "score": 145
        },
        {
            "username": "Morgan",
            "score": 138
        },
        {
            "username": "Alex",
            "score": 107
        },
        {
            "username": "Jamie",
            "score": 95
        },
        {
            "username": "Chris",
            "score": 84
        },
        {
            "username": "Sam",
            "score": 80
        },
        {
            "username": "Taylor",
            "score": 73
        },
        {
            "username": "Casey",
            "score": 42
        },
        {
            "username": "Riley",
            "score": 21
        }
    ],
    "lastPlayer": "rob​"
}